Battleships/__init__.py
Battleships/components.py
Battleships/game_engine.py
Battleships/main.py
Battleships/mp_game_engine.py
battleships_source/__init__.py
battleships_source/components.py
battleships_source/game_engine.py
battleships_source/main.py
battleships_source/mp_game_engine.py
tests/__init__.py
tests/test_functionality.py
tests/test_helper_functions.py
tests/test_students.py
battleships_solar_sausage-1.0.0.dist-info/LICENSE.txt
battleships_solar_sausage-1.0.0.dist-info/METADATA
battleships_solar_sausage-1.0.0.dist-info/WHEEL
battleships_solar_sausage-1.0.0.dist-info/entry_points.txt
battleships_solar_sausage-1.0.0.dist-info/top_level.txt
battleships_solar_sausage-1.0.0.dist-info/RECORD
