Metadata-Version: 2.1
Name: battleships-solar-sausage
Version: 1.0.0
Summary: Battleships game for uni coursework.
Home-page: https://github.com/solar-sausage/Battleships-uni-coursework-
Author: Solar Sausage
License-File: LICENSE.txt
Requires-Dist: flask
